outage/__init__.py
outage/_nbdev.py
outage/collation.py
outage/deployment.py
outage/retrieval.py
outage-0.0.2.dist-info/LICENSE
outage-0.0.2.dist-info/METADATA
outage-0.0.2.dist-info/WHEEL
outage-0.0.2.dist-info/top_level.txt
outage-0.0.2.dist-info/RECORD
