Metadata-Version: 2.1
Name: outage
Version: 0.0.2
Summary: Library for retrieving, parsing, and collating power outage data for the British electricity system.
Home-page: https://github.com/AyrtonB/Outage-Watch
Author: Ayrton Bourn
Author-email: ayrtonbourn@outlook.com
License: UNKNOWN
Platform: UNKNOWN
Classifier: Programming Language :: Python :: 3
Requires-Python: >=3.6
